{
  "tableData": {
     "//": "最後唔可以加逗號，未完先可以加",
     "body": [
       
      {"brand": "ASUS", "model": "ZenBook 14 UX425EA", "cpu": " i7-1165G7", "display_card": "Iris Xᵉ Graphics", "ram": "16 GB", "storage": "512 GB", "screen_Size": "14 inch", "weight": "1.17 kg", "battery": "67 Wh", "battery_life": "21 hrs", "evo": "N/A", "ram_replace": "✘", "disk_replace": "✔"},
      
       {"brand": "Tiger Nixon", "model": "System Architect", "cpu": "$320,800", "display_card": "2011/04/25", "ram": "Edinburgh", "storage": "23", "screen_Size": "23", "weight": "23", "battery": "23", "battery_life": "23", "evo": "23", "ram_replace": "23", "disk_replace": "23"}
   
    ],
      
    "//": "最後唔可以加逗號，未完先可以加",
    "headings": [
      
      {
        "title": "Brand",
        "data": "brand"
      },
      {
        "title": "Model",
        "data": "model"
      },
      {
        "title": "Processor",
        "data": "cpu"
      },
      {
        "title": "Processor",
        "data": "display_card"
      },
      {
        "title": "Memory",
        "data": "ram"
      },
      {
        "title": "Storage",
        "data": "storage"
      },
      {
        "title": "Screen Size",
        "data": "screen_Size"
      },
      {
        "title": "Weight",
        "data": "weight"
      },
      {
        "title": "Battery",
        "data": "battery"
      },
      {
        "title": "Battery life",
        "data": "battery_life"
      },
      {
        "title": "Intel Evo",
        "data": "evo"
      },
      {
        "title": "Memory replace",
        "data": "ram_replace"
      },
      {
        "title": "Disk replace",
        "data": "disk_replace"
      }
      
    ]
    
   
  }
}
